databaseautomationhuz/__init__.py
databaseautomationhuz/mongo_crud.py
databaseautomationhuz-0.0.12.dist-info/LICENSE
databaseautomationhuz-0.0.12.dist-info/METADATA
databaseautomationhuz-0.0.12.dist-info/WHEEL
databaseautomationhuz-0.0.12.dist-info/top_level.txt
databaseautomationhuz-0.0.12.dist-info/RECORD
